{
  "generated_at": "2025-12-20T02:01:01.196Z",
  "total_events": 75,
  "categories": [
    {
      "name": "American Football",
      "name_es": "Fútbol Americano",
      "slug": "futbol-americano",
      "canonical_url": "https://tarjetarojaenvivo.live/categoria/futbol-americano"
    },
    {
      "name": "Basketball",
      "name_es": "Baloncesto",
      "slug": "baloncesto",
      "canonical_url": "https://tarjetarojaenvivo.live/categoria/baloncesto"
    },
    {
      "name": "Combat Sports",
      "name_es": "Deportes de Combate",
      "slug": "deportes-de-combate",
      "canonical_url": "https://tarjetarojaenvivo.live/categoria/deportes-de-combate"
    },
    {
      "name": "Cricket",
      "name_es": "Cricket",
      "slug": "cricket",
      "canonical_url": "https://tarjetarojaenvivo.live/categoria/cricket"
    },
    {
      "name": "Darts",
      "name_es": "Dardos",
      "slug": "dardos",
      "canonical_url": "https://tarjetarojaenvivo.live/categoria/dardos"
    },
    {
      "name": "Football",
      "name_es": "Fútbol",
      "slug": "futbol",
      "canonical_url": "https://tarjetarojaenvivo.live/categoria/futbol"
    },
    {
      "name": "Ice Hockey",
      "name_es": "Hockey sobre Hielo",
      "slug": "hockey-sobre-hielo",
      "canonical_url": "https://tarjetarojaenvivo.live/categoria/hockey-sobre-hielo"
    },
    {
      "name": "Wrestling",
      "name_es": "Lucha Libre",
      "slug": "lucha-libre",
      "canonical_url": "https://tarjetarojaenvivo.live/categoria/lucha-libre"
    },
    {
      "name": "24/7 Streams",
      "name_es": "24/7 Streams",
      "slug": "24-7-streams",
      "canonical_url": "https://tarjetarojaenvivo.live/categoria/24-7-streams"
    }
  ],
  "events": [
    {
      "id": 15163,
      "slug": "9-alabama-vs-8-oklahoma-first-round",
      "canonical_url": "https://tarjetarojaenvivo.live/eventos/cfp/ala-ou",
      "meta": {
        "title": "#9 Alabama vs. #8 Oklahoma (First Round) EN VIVO - Tarjeta Roja TV",
        "description": "Ver #9 Alabama vs. #8 Oklahoma (First Round) en vivo gratis el sábado 20 de diciembre de 2025",
        "keywords": "rojadirecta, tarjeta roja, rojadirecta tv, pirlotv, tarjeta roja tv, rojadirecta en vivo, tarjeta roja directa, tarjeta roja en vivo, pirlo tv rojadirecta, roja directa pirlo, tarjeta roja futbol en vivo, roja directa en vivo fútbol gratis, tarjeta roja fútbol en vivo, pirlo tv tarjeta roja, tarjeta roja tv en vivo, roja tv, la roja directa, rojadirecta tv en vivo, roja dirécta, #9 Alabama vs. #8 Oklahoma (First Round), Fútbol Americano"
      },
      "event": {
        "start_time": "2025-12-20T01:00:00.000Z",
        "end_time": "2025-12-20T05:00:00.000Z",
        "status": "en vivo"
      },
      "technical": {
        "last_modified": "2025-12-20T02:01:01.196Z",
        "changefreq": "hourly",
        "priority": 0.85
      }
    },
    {
      "id": 15164,
      "slug": "10-miami-vs-7-texas-a-m-first-round",
      "canonical_url": "https://tarjetarojaenvivo.live/eventos/cfp/mia-tam",
      "meta": {
        "title": "#10 Miami vs. #7 Texas A&M (First Round) EN VIVO - Tarjeta Roja TV",
        "description": "Ver #10 Miami vs. #7 Texas A&M (First Round) en vivo gratis el sábado 20 de diciembre de 2025",
        "keywords": "rojadirecta, tarjeta roja, rojadirecta tv, pirlotv, tarjeta roja tv, rojadirecta en vivo, tarjeta roja directa, tarjeta roja en vivo, pirlo tv rojadirecta, roja directa pirlo, tarjeta roja futbol en vivo, roja directa en vivo fútbol gratis, tarjeta roja fútbol en vivo, pirlo tv tarjeta roja, tarjeta roja tv en vivo, roja tv, la roja directa, rojadirecta tv en vivo, roja dirécta, #10 Miami vs. #7 Texas A&M (First Round), Fútbol Americano"
      },
      "event": {
        "start_time": "2025-12-20T17:00:00.000Z",
        "end_time": "2025-12-20T21:00:00.000Z",
        "status": "próximamente"
      },
      "technical": {
        "last_modified": "2025-12-20T02:01:01.196Z",
        "changefreq": "hourly",
        "priority": 0.85
      }
    },
    {
      "id": 15165,
      "slug": "11-tulane-vs-6-ole-miss-first-round",
      "canonical_url": "https://tarjetarojaenvivo.live/eventos/cfp/tuln-miss",
      "meta": {
        "title": "#11 Tulane vs. #6 Ole Miss (First Round) EN VIVO - Tarjeta Roja TV",
        "description": "Ver #11 Tulane vs. #6 Ole Miss (First Round) en vivo gratis el sábado 20 de diciembre de 2025",
        "keywords": "rojadirecta, tarjeta roja, rojadirecta tv, pirlotv, tarjeta roja tv, rojadirecta en vivo, tarjeta roja directa, tarjeta roja en vivo, pirlo tv rojadirecta, roja directa pirlo, tarjeta roja futbol en vivo, roja directa en vivo fútbol gratis, tarjeta roja fútbol en vivo, pirlo tv tarjeta roja, tarjeta roja tv en vivo, roja tv, la roja directa, rojadirecta tv en vivo, roja dirécta, #11 Tulane vs. #6 Ole Miss (First Round), Fútbol Americano"
      },
      "event": {
        "start_time": "2025-12-20T20:30:00.000Z",
        "end_time": "2025-12-21T00:30:00.000Z",
        "status": "próximamente"
      },
      "technical": {
        "last_modified": "2025-12-20T02:01:01.196Z",
        "changefreq": "hourly",
        "priority": 0.85
      }
    },
    {
      "id": 15066,
      "slug": "philadelphia-eagles-vs-washington-commanders",
      "canonical_url": "https://tarjetarojaenvivo.live/eventos/nfl/2025-12-20/phi-wsh",
      "meta": {
        "title": "Philadelphia Eagles vs. Washington Commanders EN VIVO - Tarjeta Roja TV",
        "description": "Ver Philadelphia Eagles vs. Washington Commanders en vivo gratis el sábado 20 de diciembre de 2025",
        "keywords": "rojadirecta, tarjeta roja, rojadirecta tv, pirlotv, tarjeta roja tv, rojadirecta en vivo, tarjeta roja directa, tarjeta roja en vivo, pirlo tv rojadirecta, roja directa pirlo, tarjeta roja futbol en vivo, roja directa en vivo fútbol gratis, tarjeta roja fútbol en vivo, pirlo tv tarjeta roja, tarjeta roja tv en vivo, roja tv, la roja directa, rojadirecta tv en vivo, roja dirécta, Philadelphia Eagles vs. Washington Commanders, Fútbol Americano"
      },
      "event": {
        "start_time": "2025-12-20T22:00:00.000Z",
        "end_time": "2025-12-21T01:30:00.000Z",
        "status": "próximamente"
      },
      "technical": {
        "last_modified": "2025-12-20T02:01:01.196Z",
        "changefreq": "hourly",
        "priority": 0.85
      }
    },
    {
      "id": 15166,
      "slug": "12-jmu-vs-5-oregon-first-round",
      "canonical_url": "https://tarjetarojaenvivo.live/eventos/cfp/jmu-ore",
      "meta": {
        "title": "#12 JMU vs. #5 Oregon (First Round) EN VIVO - Tarjeta Roja TV",
        "description": "Ver #12 JMU vs. #5 Oregon (First Round) en vivo gratis el domingo 21 de diciembre de 2025",
        "keywords": "rojadirecta, tarjeta roja, rojadirecta tv, pirlotv, tarjeta roja tv, rojadirecta en vivo, tarjeta roja directa, tarjeta roja en vivo, pirlo tv rojadirecta, roja directa pirlo, tarjeta roja futbol en vivo, roja directa en vivo fútbol gratis, tarjeta roja fútbol en vivo, pirlo tv tarjeta roja, tarjeta roja tv en vivo, roja tv, la roja directa, rojadirecta tv en vivo, roja dirécta, #12 JMU vs. #5 Oregon (First Round), Fútbol Americano"
      },
      "event": {
        "start_time": "2025-12-21T00:30:00.000Z",
        "end_time": "2025-12-21T04:30:00.000Z",
        "status": "próximamente"
      },
      "technical": {
        "last_modified": "2025-12-20T02:01:01.197Z",
        "changefreq": "hourly",
        "priority": 0.85
      }
    },
    {
      "id": 15070,
      "slug": "green-bay-packers-vs-chicago-bears",
      "canonical_url": "https://tarjetarojaenvivo.live/eventos/nfl/2025-12-20/gb-chi",
      "meta": {
        "title": "Green Bay Packers vs. Chicago Bears EN VIVO - Tarjeta Roja TV",
        "description": "Ver Green Bay Packers vs. Chicago Bears en vivo gratis el domingo 21 de diciembre de 2025",
        "keywords": "rojadirecta, tarjeta roja, rojadirecta tv, pirlotv, tarjeta roja tv, rojadirecta en vivo, tarjeta roja directa, tarjeta roja en vivo, pirlo tv rojadirecta, roja directa pirlo, tarjeta roja futbol en vivo, roja directa en vivo fútbol gratis, tarjeta roja fútbol en vivo, pirlo tv tarjeta roja, tarjeta roja tv en vivo, roja tv, la roja directa, rojadirecta tv en vivo, roja dirécta, Green Bay Packers vs. Chicago Bears, Fútbol Americano"
      },
      "event": {
        "start_time": "2025-12-21T01:20:00.000Z",
        "end_time": "2025-12-21T04:50:00.000Z",
        "status": "próximamente"
      },
      "technical": {
        "last_modified": "2025-12-20T02:01:01.197Z",
        "changefreq": "hourly",
        "priority": 0.85
      }
    },
    {
      "id": 15072,
      "slug": "buffalo-bills-vs-cleveland-browns",
      "canonical_url": "https://tarjetarojaenvivo.live/eventos/nfl/2025-12-21/buf-cle",
      "meta": {
        "title": "Buffalo Bills vs. Cleveland Browns EN VIVO - Tarjeta Roja TV",
        "description": "Ver Buffalo Bills vs. Cleveland Browns en vivo gratis el domingo 21 de diciembre de 2025",
        "keywords": "rojadirecta, tarjeta roja, rojadirecta tv, pirlotv, tarjeta roja tv, rojadirecta en vivo, tarjeta roja directa, tarjeta roja en vivo, pirlo tv rojadirecta, roja directa pirlo, tarjeta roja futbol en vivo, roja directa en vivo fútbol gratis, tarjeta roja fútbol en vivo, pirlo tv tarjeta roja, tarjeta roja tv en vivo, roja tv, la roja directa, rojadirecta tv en vivo, roja dirécta, Buffalo Bills vs. Cleveland Browns, Fútbol Americano"
      },
      "event": {
        "start_time": "2025-12-21T18:00:00.000Z",
        "end_time": "2025-12-21T21:30:00.000Z",
        "status": "próximamente"
      },
      "technical": {
        "last_modified": "2025-12-20T02:01:01.197Z",
        "changefreq": "hourly",
        "priority": 0.85
      }
    },
    {
      "id": 15074,
      "slug": "los-angeles-chargers-vs-dallas-cowboys",
      "canonical_url": "https://tarjetarojaenvivo.live/eventos/nfl/2025-12-21/lac-dal",
      "meta": {
        "title": "Los Angeles Chargers vs. Dallas Cowboys EN VIVO - Tarjeta Roja TV",
        "description": "Ver Los Angeles Chargers vs. Dallas Cowboys en vivo gratis el domingo 21 de diciembre de 2025",
        "keywords": "rojadirecta, tarjeta roja, rojadirecta tv, pirlotv, tarjeta roja tv, rojadirecta en vivo, tarjeta roja directa, tarjeta roja en vivo, pirlo tv rojadirecta, roja directa pirlo, tarjeta roja futbol en vivo, roja directa en vivo fútbol gratis, tarjeta roja fútbol en vivo, pirlo tv tarjeta roja, tarjeta roja tv en vivo, roja tv, la roja directa, rojadirecta tv en vivo, roja dirécta, Los Angeles Chargers vs. Dallas Cowboys, Fútbol Americano"
      },
      "event": {
        "start_time": "2025-12-21T18:00:00.000Z",
        "end_time": "2025-12-21T21:30:00.000Z",
        "status": "próximamente"
      },
      "technical": {
        "last_modified": "2025-12-20T02:01:01.197Z",
        "changefreq": "hourly",
        "priority": 0.85
      }
    },
    {
      "id": 15075,
      "slug": "kansas-city-chiefs-vs-tennessee-titans",
      "canonical_url": "https://tarjetarojaenvivo.live/eventos/nfl/2025-12-21/kc-ten",
      "meta": {
        "title": "Kansas City Chiefs vs. Tennessee Titans EN VIVO - Tarjeta Roja TV",
        "description": "Ver Kansas City Chiefs vs. Tennessee Titans en vivo gratis el domingo 21 de diciembre de 2025",
        "keywords": "rojadirecta, tarjeta roja, rojadirecta tv, pirlotv, tarjeta roja tv, rojadirecta en vivo, tarjeta roja directa, tarjeta roja en vivo, pirlo tv rojadirecta, roja directa pirlo, tarjeta roja futbol en vivo, roja directa en vivo fútbol gratis, tarjeta roja fútbol en vivo, pirlo tv tarjeta roja, tarjeta roja tv en vivo, roja tv, la roja directa, rojadirecta tv en vivo, roja dirécta, Kansas City Chiefs vs. Tennessee Titans, Fútbol Americano"
      },
      "event": {
        "start_time": "2025-12-21T18:00:00.000Z",
        "end_time": "2025-12-21T21:30:00.000Z",
        "status": "próximamente"
      },
      "technical": {
        "last_modified": "2025-12-20T02:01:01.197Z",
        "changefreq": "hourly",
        "priority": 0.85
      }
    },
    {
      "id": 15078,
      "slug": "cincinnati-bengals-vs-miami-dolphins",
      "canonical_url": "https://tarjetarojaenvivo.live/eventos/nfl/2025-12-21/cin-mia",
      "meta": {
        "title": "Cincinnati Bengals vs. Miami Dolphins EN VIVO - Tarjeta Roja TV",
        "description": "Ver Cincinnati Bengals vs. Miami Dolphins en vivo gratis el domingo 21 de diciembre de 2025",
        "keywords": "rojadirecta, tarjeta roja, rojadirecta tv, pirlotv, tarjeta roja tv, rojadirecta en vivo, tarjeta roja directa, tarjeta roja en vivo, pirlo tv rojadirecta, roja directa pirlo, tarjeta roja futbol en vivo, roja directa en vivo fútbol gratis, tarjeta roja fútbol en vivo, pirlo tv tarjeta roja, tarjeta roja tv en vivo, roja tv, la roja directa, rojadirecta tv en vivo, roja dirécta, Cincinnati Bengals vs. Miami Dolphins, Fútbol Americano"
      },
      "event": {
        "start_time": "2025-12-21T18:00:00.000Z",
        "end_time": "2025-12-21T21:30:00.000Z",
        "status": "próximamente"
      },
      "technical": {
        "last_modified": "2025-12-20T02:01:01.197Z",
        "changefreq": "hourly",
        "priority": 0.85
      }
    },
    {
      "id": 15080,
      "slug": "new-york-jets-vs-new-orleans-saints",
      "canonical_url": "https://tarjetarojaenvivo.live/eventos/nfl/2025-12-21/nyj-no",
      "meta": {
        "title": "New York Jets vs. New Orleans Saints EN VIVO - Tarjeta Roja TV",
        "description": "Ver New York Jets vs. New Orleans Saints en vivo gratis el domingo 21 de diciembre de 2025",
        "keywords": "rojadirecta, tarjeta roja, rojadirecta tv, pirlotv, tarjeta roja tv, rojadirecta en vivo, tarjeta roja directa, tarjeta roja en vivo, pirlo tv rojadirecta, roja directa pirlo, tarjeta roja futbol en vivo, roja directa en vivo fútbol gratis, tarjeta roja fútbol en vivo, pirlo tv tarjeta roja, tarjeta roja tv en vivo, roja tv, la roja directa, rojadirecta tv en vivo, roja dirécta, New York Jets vs. New Orleans Saints, Fútbol Americano"
      },
      "event": {
        "start_time": "2025-12-21T18:00:00.000Z",
        "end_time": "2025-12-21T21:30:00.000Z",
        "status": "próximamente"
      },
      "technical": {
        "last_modified": "2025-12-20T02:01:01.197Z",
        "changefreq": "hourly",
        "priority": 0.85
      }
    },
    {
      "id": 15081,
      "slug": "minnesota-vikings-vs-new-york-giants",
      "canonical_url": "https://tarjetarojaenvivo.live/eventos/nfl/2025-12-21/min-nyg",
      "meta": {
        "title": "Minnesota Vikings vs. New York Giants EN VIVO - Tarjeta Roja TV",
        "description": "Ver Minnesota Vikings vs. New York Giants en vivo gratis el domingo 21 de diciembre de 2025",
        "keywords": "rojadirecta, tarjeta roja, rojadirecta tv, pirlotv, tarjeta roja tv, rojadirecta en vivo, tarjeta roja directa, tarjeta roja en vivo, pirlo tv rojadirecta, roja directa pirlo, tarjeta roja futbol en vivo, roja directa en vivo fútbol gratis, tarjeta roja fútbol en vivo, pirlo tv tarjeta roja, tarjeta roja tv en vivo, roja tv, la roja directa, rojadirecta tv en vivo, roja dirécta, Minnesota Vikings vs. New York Giants, Fútbol Americano"
      },
      "event": {
        "start_time": "2025-12-21T18:00:00.000Z",
        "end_time": "2025-12-21T21:30:00.000Z",
        "status": "próximamente"
      },
      "technical": {
        "last_modified": "2025-12-20T02:01:01.197Z",
        "changefreq": "hourly",
        "priority": 0.85
      }
    },
    {
      "id": 15082,
      "slug": "tampa-bay-buccaneers-vs-carolina-panthers",
      "canonical_url": "https://tarjetarojaenvivo.live/eventos/nfl/2025-12-21/tb-car",
      "meta": {
        "title": "Tampa Bay Buccaneers vs. Carolina Panthers EN VIVO - Tarjeta Roja TV",
        "description": "Ver Tampa Bay Buccaneers vs. Carolina Panthers en vivo gratis el domingo 21 de diciembre de 2025",
        "keywords": "rojadirecta, tarjeta roja, rojadirecta tv, pirlotv, tarjeta roja tv, rojadirecta en vivo, tarjeta roja directa, tarjeta roja en vivo, pirlo tv rojadirecta, roja directa pirlo, tarjeta roja futbol en vivo, roja directa en vivo fútbol gratis, tarjeta roja fútbol en vivo, pirlo tv tarjeta roja, tarjeta roja tv en vivo, roja tv, la roja directa, rojadirecta tv en vivo, roja dirécta, Tampa Bay Buccaneers vs. Carolina Panthers, Fútbol Americano"
      },
      "event": {
        "start_time": "2025-12-21T18:00:00.000Z",
        "end_time": "2025-12-21T21:30:00.000Z",
        "status": "próximamente"
      },
      "technical": {
        "last_modified": "2025-12-20T02:01:01.197Z",
        "changefreq": "hourly",
        "priority": 0.85
      }
    },
    {
      "id": 15083,
      "slug": "jacksonville-jaguars-vs-denver-broncos",
      "canonical_url": "https://tarjetarojaenvivo.live/eventos/nfl/2025-12-21/jax-den",
      "meta": {
        "title": "Jacksonville Jaguars vs. Denver Broncos EN VIVO - Tarjeta Roja TV",
        "description": "Ver Jacksonville Jaguars vs. Denver Broncos en vivo gratis el domingo 21 de diciembre de 2025",
        "keywords": "rojadirecta, tarjeta roja, rojadirecta tv, pirlotv, tarjeta roja tv, rojadirecta en vivo, tarjeta roja directa, tarjeta roja en vivo, pirlo tv rojadirecta, roja directa pirlo, tarjeta roja futbol en vivo, roja directa en vivo fútbol gratis, tarjeta roja fútbol en vivo, pirlo tv tarjeta roja, tarjeta roja tv en vivo, roja tv, la roja directa, rojadirecta tv en vivo, roja dirécta, Jacksonville Jaguars vs. Denver Broncos, Fútbol Americano"
      },
      "event": {
        "start_time": "2025-12-21T21:05:00.000Z",
        "end_time": "2025-12-22T00:35:00.000Z",
        "status": "próximamente"
      },
      "technical": {
        "last_modified": "2025-12-20T02:01:01.197Z",
        "changefreq": "hourly",
        "priority": 0.85
      }
    },
    {
      "id": 15084,
      "slug": "atlanta-falcons-vs-arizona-cardinals",
      "canonical_url": "https://tarjetarojaenvivo.live/eventos/nfl/2025-12-21/atl-ari",
      "meta": {
        "title": "Atlanta Falcons vs. Arizona Cardinals EN VIVO - Tarjeta Roja TV",
        "description": "Ver Atlanta Falcons vs. Arizona Cardinals en vivo gratis el domingo 21 de diciembre de 2025",
        "keywords": "rojadirecta, tarjeta roja, rojadirecta tv, pirlotv, tarjeta roja tv, rojadirecta en vivo, tarjeta roja directa, tarjeta roja en vivo, pirlo tv rojadirecta, roja directa pirlo, tarjeta roja futbol en vivo, roja directa en vivo fútbol gratis, tarjeta roja fútbol en vivo, pirlo tv tarjeta roja, tarjeta roja tv en vivo, roja tv, la roja directa, rojadirecta tv en vivo, roja dirécta, Atlanta Falcons vs. Arizona Cardinals, Fútbol Americano"
      },
      "event": {
        "start_time": "2025-12-21T21:05:00.000Z",
        "end_time": "2025-12-22T00:35:00.000Z",
        "status": "próximamente"
      },
      "technical": {
        "last_modified": "2025-12-20T02:01:01.197Z",
        "changefreq": "hourly",
        "priority": 0.85
      }
    },
    {
      "id": 15085,
      "slug": "pittsburgh-steelers-vs-detroit-lions",
      "canonical_url": "https://tarjetarojaenvivo.live/eventos/nfl/2025-12-21/pit-det",
      "meta": {
        "title": "Pittsburgh Steelers vs. Detroit Lions EN VIVO - Tarjeta Roja TV",
        "description": "Ver Pittsburgh Steelers vs. Detroit Lions en vivo gratis el domingo 21 de diciembre de 2025",
        "keywords": "rojadirecta, tarjeta roja, rojadirecta tv, pirlotv, tarjeta roja tv, rojadirecta en vivo, tarjeta roja directa, tarjeta roja en vivo, pirlo tv rojadirecta, roja directa pirlo, tarjeta roja futbol en vivo, roja directa en vivo fútbol gratis, tarjeta roja fútbol en vivo, pirlo tv tarjeta roja, tarjeta roja tv en vivo, roja tv, la roja directa, rojadirecta tv en vivo, roja dirécta, Pittsburgh Steelers vs. Detroit Lions, Fútbol Americano"
      },
      "event": {
        "start_time": "2025-12-21T21:25:00.000Z",
        "end_time": "2025-12-22T00:55:00.000Z",
        "status": "próximamente"
      },
      "technical": {
        "last_modified": "2025-12-20T02:01:01.197Z",
        "changefreq": "hourly",
        "priority": 0.85
      }
    },
    {
      "id": 15086,
      "slug": "las-vegas-raiders-vs-houston-texans",
      "canonical_url": "https://tarjetarojaenvivo.live/eventos/nfl/2025-12-21/lv-hou",
      "meta": {
        "title": "Las Vegas Raiders vs. Houston Texans EN VIVO - Tarjeta Roja TV",
        "description": "Ver Las Vegas Raiders vs. Houston Texans en vivo gratis el domingo 21 de diciembre de 2025",
        "keywords": "rojadirecta, tarjeta roja, rojadirecta tv, pirlotv, tarjeta roja tv, rojadirecta en vivo, tarjeta roja directa, tarjeta roja en vivo, pirlo tv rojadirecta, roja directa pirlo, tarjeta roja futbol en vivo, roja directa en vivo fútbol gratis, tarjeta roja fútbol en vivo, pirlo tv tarjeta roja, tarjeta roja tv en vivo, roja tv, la roja directa, rojadirecta tv en vivo, roja dirécta, Las Vegas Raiders vs. Houston Texans, Fútbol Americano"
      },
      "event": {
        "start_time": "2025-12-21T21:25:00.000Z",
        "end_time": "2025-12-22T00:55:00.000Z",
        "status": "próximamente"
      },
      "technical": {
        "last_modified": "2025-12-20T02:01:01.197Z",
        "changefreq": "hourly",
        "priority": 0.85
      }
    },
    {
      "id": 15087,
      "slug": "new-england-patriots-vs-baltimore-ravens",
      "canonical_url": "https://tarjetarojaenvivo.live/eventos/nfl/2025-12-21/ne-bal",
      "meta": {
        "title": "New England Patriots vs. Baltimore Ravens EN VIVO - Tarjeta Roja TV",
        "description": "Ver New England Patriots vs. Baltimore Ravens en vivo gratis el lunes 22 de diciembre de 2025",
        "keywords": "rojadirecta, tarjeta roja, rojadirecta tv, pirlotv, tarjeta roja tv, rojadirecta en vivo, tarjeta roja directa, tarjeta roja en vivo, pirlo tv rojadirecta, roja directa pirlo, tarjeta roja futbol en vivo, roja directa en vivo fútbol gratis, tarjeta roja fútbol en vivo, pirlo tv tarjeta roja, tarjeta roja tv en vivo, roja tv, la roja directa, rojadirecta tv en vivo, roja dirécta, New England Patriots vs. Baltimore Ravens, Fútbol Americano"
      },
      "event": {
        "start_time": "2025-12-22T01:20:00.000Z",
        "end_time": "2025-12-22T04:50:00.000Z",
        "status": "próximamente"
      },
      "technical": {
        "last_modified": "2025-12-20T02:01:01.197Z",
        "changefreq": "hourly",
        "priority": 0.85
      }
    },
    {
      "id": 15088,
      "slug": "san-francisco-49ers-vs-indianapolis-colts",
      "canonical_url": "https://tarjetarojaenvivo.live/eventos/nfl/2025-12-22/sf-ind",
      "meta": {
        "title": "San Francisco 49ers vs. Indianapolis Colts EN VIVO - Tarjeta Roja TV",
        "description": "Ver San Francisco 49ers vs. Indianapolis Colts en vivo gratis el martes 23 de diciembre de 2025",
        "keywords": "rojadirecta, tarjeta roja, rojadirecta tv, pirlotv, tarjeta roja tv, rojadirecta en vivo, tarjeta roja directa, tarjeta roja en vivo, pirlo tv rojadirecta, roja directa pirlo, tarjeta roja futbol en vivo, roja directa en vivo fútbol gratis, tarjeta roja fútbol en vivo, pirlo tv tarjeta roja, tarjeta roja tv en vivo, roja tv, la roja directa, rojadirecta tv en vivo, roja dirécta, San Francisco 49ers vs. Indianapolis Colts, Fútbol Americano"
      },
      "event": {
        "start_time": "2025-12-23T01:15:00.000Z",
        "end_time": "2025-12-23T04:45:00.000Z",
        "status": "próximamente"
      },
      "technical": {
        "last_modified": "2025-12-20T02:01:01.197Z",
        "changefreq": "hourly",
        "priority": 0.85
      }
    },
    {
      "id": 15167,
      "slug": "miami-heat-vs-boston-celtics",
      "canonical_url": "https://tarjetarojaenvivo.live/eventos/nba/2025-12-19/mia-bos",
      "meta": {
        "title": "Miami Heat vs. Boston Celtics EN VIVO - Tarjeta Roja TV",
        "description": "Ver Miami Heat vs. Boston Celtics en vivo gratis el sábado 20 de diciembre de 2025",
        "keywords": "rojadirecta, tarjeta roja, rojadirecta tv, pirlotv, tarjeta roja tv, rojadirecta en vivo, tarjeta roja directa, tarjeta roja en vivo, pirlo tv rojadirecta, roja directa pirlo, tarjeta roja futbol en vivo, roja directa en vivo fútbol gratis, tarjeta roja fútbol en vivo, pirlo tv tarjeta roja, tarjeta roja tv en vivo, roja tv, la roja directa, rojadirecta tv en vivo, roja dirécta, Miami Heat vs. Boston Celtics, Baloncesto"
      },
      "event": {
        "start_time": "2025-12-20T00:00:00.000Z",
        "end_time": "2025-12-20T02:48:00.000Z",
        "status": "en vivo"
      },
      "technical": {
        "last_modified": "2025-12-20T02:01:01.197Z",
        "changefreq": "hourly",
        "priority": 0.85
      }
    },
    {
      "id": 15169,
      "slug": "philadelphia-76ers-vs-new-york-knicks",
      "canonical_url": "https://tarjetarojaenvivo.live/eventos/nba/2025-12-19/phi-ny",
      "meta": {
        "title": "Philadelphia 76ers vs. New York Knicks EN VIVO - Tarjeta Roja TV",
        "description": "Ver Philadelphia 76ers vs. New York Knicks en vivo gratis el sábado 20 de diciembre de 2025",
        "keywords": "rojadirecta, tarjeta roja, rojadirecta tv, pirlotv, tarjeta roja tv, rojadirecta en vivo, tarjeta roja directa, tarjeta roja en vivo, pirlo tv rojadirecta, roja directa pirlo, tarjeta roja futbol en vivo, roja directa en vivo fútbol gratis, tarjeta roja fútbol en vivo, pirlo tv tarjeta roja, tarjeta roja tv en vivo, roja tv, la roja directa, rojadirecta tv en vivo, roja dirécta, Philadelphia 76ers vs. New York Knicks, Baloncesto"
      },
      "event": {
        "start_time": "2025-12-20T00:00:00.000Z",
        "end_time": "2025-12-20T02:48:00.000Z",
        "status": "en vivo"
      },
      "technical": {
        "last_modified": "2025-12-20T02:01:01.197Z",
        "changefreq": "hourly",
        "priority": 0.85
      }
    },
    {
      "id": 15171,
      "slug": "san-antonio-spurs-vs-atlanta-hawks",
      "canonical_url": "https://tarjetarojaenvivo.live/eventos/nba/2025-12-19/sa-atl",
      "meta": {
        "title": "San Antonio Spurs vs. Atlanta Hawks EN VIVO - Tarjeta Roja TV",
        "description": "Ver San Antonio Spurs vs. Atlanta Hawks en vivo gratis el sábado 20 de diciembre de 2025",
        "keywords": "rojadirecta, tarjeta roja, rojadirecta tv, pirlotv, tarjeta roja tv, rojadirecta en vivo, tarjeta roja directa, tarjeta roja en vivo, pirlo tv rojadirecta, roja directa pirlo, tarjeta roja futbol en vivo, roja directa en vivo fútbol gratis, tarjeta roja fútbol en vivo, pirlo tv tarjeta roja, tarjeta roja tv en vivo, roja tv, la roja directa, rojadirecta tv en vivo, roja dirécta, San Antonio Spurs vs. Atlanta Hawks, Baloncesto"
      },
      "event": {
        "start_time": "2025-12-20T00:30:00.000Z",
        "end_time": "2025-12-20T03:18:00.000Z",
        "status": "en vivo"
      },
      "technical": {
        "last_modified": "2025-12-20T02:01:01.197Z",
        "changefreq": "hourly",
        "priority": 0.85
      }
    },
    {
      "id": 15173,
      "slug": "chicago-bulls-vs-cleveland-cavaliers",
      "canonical_url": "https://tarjetarojaenvivo.live/eventos/nba/2025-12-19/chi-cle",
      "meta": {
        "title": "Chicago Bulls vs. Cleveland Cavaliers EN VIVO - Tarjeta Roja TV",
        "description": "Ver Chicago Bulls vs. Cleveland Cavaliers en vivo gratis el sábado 20 de diciembre de 2025",
        "keywords": "rojadirecta, tarjeta roja, rojadirecta tv, pirlotv, tarjeta roja tv, rojadirecta en vivo, tarjeta roja directa, tarjeta roja en vivo, pirlo tv rojadirecta, roja directa pirlo, tarjeta roja futbol en vivo, roja directa en vivo fútbol gratis, tarjeta roja fútbol en vivo, pirlo tv tarjeta roja, tarjeta roja tv en vivo, roja tv, la roja directa, rojadirecta tv en vivo, roja dirécta, Chicago Bulls vs. Cleveland Cavaliers, Baloncesto"
      },
      "event": {
        "start_time": "2025-12-20T00:30:00.000Z",
        "end_time": "2025-12-20T03:18:00.000Z",
        "status": "en vivo"
      },
      "technical": {
        "last_modified": "2025-12-20T02:01:01.197Z",
        "changefreq": "hourly",
        "priority": 0.85
      }
    },
    {
      "id": 15175,
      "slug": "oklahoma-city-thunder-vs-minnesota-timberwolves",
      "canonical_url": "https://tarjetarojaenvivo.live/eventos/nba/2025-12-19/okc-min",
      "meta": {
        "title": "Oklahoma City Thunder vs. Minnesota Timberwolves EN VIVO - Tarjeta Roja TV",
        "description": "Ver Oklahoma City Thunder vs. Minnesota Timberwolves en vivo gratis el sábado 20 de diciembre de 2025",
        "keywords": "rojadirecta, tarjeta roja, rojadirecta tv, pirlotv, tarjeta roja tv, rojadirecta en vivo, tarjeta roja directa, tarjeta roja en vivo, pirlo tv rojadirecta, roja directa pirlo, tarjeta roja futbol en vivo, roja directa en vivo fútbol gratis, tarjeta roja fútbol en vivo, pirlo tv tarjeta roja, tarjeta roja tv en vivo, roja tv, la roja directa, rojadirecta tv en vivo, roja dirécta, Oklahoma City Thunder vs. Minnesota Timberwolves, Baloncesto"
      },
      "event": {
        "start_time": "2025-12-20T02:30:00.000Z",
        "end_time": "2025-12-20T05:18:00.000Z",
        "status": "próximamente"
      },
      "technical": {
        "last_modified": "2025-12-20T02:01:01.197Z",
        "changefreq": "hourly",
        "priority": 0.85
      }
    },
    {
      "id": 15134,
      "slug": "jake-paul-vs-anthony-joshua",
      "canonical_url": "https://tarjetarojaenvivo.live/eventos/jake-paul-vs.-anthony-joshua",
      "meta": {
        "title": "Jake Paul vs. Anthony Joshua EN VIVO - Tarjeta Roja TV",
        "description": "Ver Jake Paul vs. Anthony Joshua en vivo gratis el sábado 20 de diciembre de 2025",
        "keywords": "rojadirecta, tarjeta roja, rojadirecta tv, pirlotv, tarjeta roja tv, rojadirecta en vivo, tarjeta roja directa, tarjeta roja en vivo, pirlo tv rojadirecta, roja directa pirlo, tarjeta roja futbol en vivo, roja directa en vivo fútbol gratis, tarjeta roja fútbol en vivo, pirlo tv tarjeta roja, tarjeta roja tv en vivo, roja tv, la roja directa, rojadirecta tv en vivo, roja dirécta, Jake Paul vs. Anthony Joshua, Deportes de Combate"
      },
      "event": {
        "start_time": "2025-12-20T01:00:00.000Z",
        "end_time": "2025-12-20T09:00:00.000Z",
        "status": "en vivo"
      },
      "technical": {
        "last_modified": "2025-12-20T02:01:01.197Z",
        "changefreq": "hourly",
        "priority": 0.85
      }
    },
    {
      "id": 15132,
      "slug": "misfits-mania-andrew-tate-vs-chase-demoor",
      "canonical_url": "https://tarjetarojaenvivo.live/eventos/misfits-mania/2025-12-20",
      "meta": {
        "title": "Misfits Mania: Andrew Tate vs. Chase DeMoor EN VIVO - Tarjeta Roja TV",
        "description": "Ver Misfits Mania: Andrew Tate vs. Chase DeMoor en vivo gratis el sábado 20 de diciembre de 2025",
        "keywords": "rojadirecta, tarjeta roja, rojadirecta tv, pirlotv, tarjeta roja tv, rojadirecta en vivo, tarjeta roja directa, tarjeta roja en vivo, pirlo tv rojadirecta, roja directa pirlo, tarjeta roja futbol en vivo, roja directa en vivo fútbol gratis, tarjeta roja fútbol en vivo, pirlo tv tarjeta roja, tarjeta roja tv en vivo, roja tv, la roja directa, rojadirecta tv en vivo, roja dirécta, Misfits Mania: Andrew Tate vs. Chase DeMoor, Deportes de Combate"
      },
      "event": {
        "start_time": "2025-12-20T19:00:00.000Z",
        "end_time": "2025-12-21T01:00:00.000Z",
        "status": "próximamente"
      },
      "technical": {
        "last_modified": "2025-12-20T02:01:01.197Z",
        "changefreq": "hourly",
        "priority": 0.85
      }
    },
    {
      "id": 14284,
      "slug": "ufc-324-gaethje-vs-pimblett",
      "canonical_url": "https://tarjetarojaenvivo.live/eventos/ufc-324",
      "meta": {
        "title": "UFC 324: Gaethje vs. Pimblett EN VIVO - Tarjeta Roja TV",
        "description": "Ver UFC 324: Gaethje vs. Pimblett en vivo gratis el domingo 25 de enero de 2026",
        "keywords": "rojadirecta, tarjeta roja, rojadirecta tv, pirlotv, tarjeta roja tv, rojadirecta en vivo, tarjeta roja directa, tarjeta roja en vivo, pirlo tv rojadirecta, roja directa pirlo, tarjeta roja futbol en vivo, roja directa en vivo fútbol gratis, tarjeta roja fútbol en vivo, pirlo tv tarjeta roja, tarjeta roja tv en vivo, roja tv, la roja directa, rojadirecta tv en vivo, roja dirécta, UFC 324: Gaethje vs. Pimblett, Deportes de Combate"
      },
      "event": {
        "start_time": "2026-01-25T00:00:00.000Z",
        "end_time": "2026-01-25T08:00:00.000Z",
        "status": "próximamente"
      },
      "technical": {
        "last_modified": "2025-12-20T02:01:01.197Z",
        "changefreq": "hourly",
        "priority": 0.85
      }
    },
    {
      "id": 15121,
      "slug": "australia-vs-england",
      "canonical_url": "https://tarjetarojaenvivo.live/eventos/cricket/2025/au-en/3rd-test",
      "meta": {
        "title": "Australia vs. England EN VIVO - Tarjeta Roja TV",
        "description": "Ver Australia vs. England en vivo gratis el viernes 19 de diciembre de 2025",
        "keywords": "rojadirecta, tarjeta roja, rojadirecta tv, pirlotv, tarjeta roja tv, rojadirecta en vivo, tarjeta roja directa, tarjeta roja en vivo, pirlo tv rojadirecta, roja directa pirlo, tarjeta roja futbol en vivo, roja directa en vivo fútbol gratis, tarjeta roja fútbol en vivo, pirlo tv tarjeta roja, tarjeta roja tv en vivo, roja tv, la roja directa, rojadirecta tv en vivo, roja dirécta, Australia vs. England, Cricket"
      },
      "event": {
        "start_time": "2025-12-19T23:30:00.000Z",
        "end_time": "2025-12-20T07:30:00.000Z",
        "status": "en vivo"
      },
      "technical": {
        "last_modified": "2025-12-20T02:01:01.197Z",
        "changefreq": "hourly",
        "priority": 0.85
      }
    },
    {
      "id": 14899,
      "slug": "world-darts-championship",
      "canonical_url": "https://tarjetarojaenvivo.live/eventos/2025-world-darts-championship",
      "meta": {
        "title": "World Darts Championship EN VIVO - Tarjeta Roja TV",
        "description": "Ver World Darts Championship en vivo gratis el sábado 20 de diciembre de 2025",
        "keywords": "rojadirecta, tarjeta roja, rojadirecta tv, pirlotv, tarjeta roja tv, rojadirecta en vivo, tarjeta roja directa, tarjeta roja en vivo, pirlo tv rojadirecta, roja directa pirlo, tarjeta roja futbol en vivo, roja directa en vivo fútbol gratis, tarjeta roja fútbol en vivo, pirlo tv tarjeta roja, tarjeta roja tv en vivo, roja tv, la roja directa, rojadirecta tv en vivo, roja dirécta, World Darts Championship, Dardos"
      },
      "event": {
        "start_time": "2025-12-20T12:30:00.000Z",
        "end_time": "2025-12-20T23:30:00.000Z",
        "status": "próximamente"
      },
      "technical": {
        "last_modified": "2025-12-20T02:01:01.197Z",
        "changefreq": "hourly",
        "priority": 0.85
      }
    },
    {
      "id": 15023,
      "slug": "newcastle-united-vs-chelsea",
      "canonical_url": "https://tarjetarojaenvivo.live/eventos/premierleague/2025-12-20/new-che",
      "meta": {
        "title": "Newcastle United vs. Chelsea EN VIVO - Tarjeta Roja TV",
        "description": "Ver Newcastle United vs. Chelsea en vivo gratis el sábado 20 de diciembre de 2025",
        "keywords": "rojadirecta, tarjeta roja, rojadirecta tv, pirlotv, tarjeta roja tv, rojadirecta en vivo, tarjeta roja directa, tarjeta roja en vivo, pirlo tv rojadirecta, roja directa pirlo, tarjeta roja futbol en vivo, roja directa en vivo fútbol gratis, tarjeta roja fútbol en vivo, pirlo tv tarjeta roja, tarjeta roja tv en vivo, roja tv, la roja directa, rojadirecta tv en vivo, roja dirécta, Newcastle United vs. Chelsea, Fútbol"
      },
      "event": {
        "start_time": "2025-12-20T12:30:00.000Z",
        "end_time": "2025-12-20T15:00:00.000Z",
        "status": "próximamente"
      },
      "technical": {
        "last_modified": "2025-12-20T02:01:01.197Z",
        "changefreq": "hourly",
        "priority": 0.85
      }
    },
    {
      "id": 15005,
      "slug": "real-oviedo-vs-celta-vigo",
      "canonical_url": "https://tarjetarojaenvivo.live/eventos/laliga/2025-12-20/ovi-cel",
      "meta": {
        "title": "Real Oviedo vs. Celta Vigo EN VIVO - Tarjeta Roja TV",
        "description": "Ver Real Oviedo vs. Celta Vigo en vivo gratis el sábado 20 de diciembre de 2025",
        "keywords": "rojadirecta, tarjeta roja, rojadirecta tv, pirlotv, tarjeta roja tv, rojadirecta en vivo, tarjeta roja directa, tarjeta roja en vivo, pirlo tv rojadirecta, roja directa pirlo, tarjeta roja futbol en vivo, roja directa en vivo fútbol gratis, tarjeta roja fútbol en vivo, pirlo tv tarjeta roja, tarjeta roja tv en vivo, roja tv, la roja directa, rojadirecta tv en vivo, roja dirécta, Real Oviedo vs. Celta Vigo, Fútbol"
      },
      "event": {
        "start_time": "2025-12-20T13:00:00.000Z",
        "end_time": "2025-12-20T15:30:00.000Z",
        "status": "próximamente"
      },
      "technical": {
        "last_modified": "2025-12-20T02:01:01.197Z",
        "changefreq": "hourly",
        "priority": 0.85
      }
    },
    {
      "id": 15015,
      "slug": "fc-augsburg-vs-werder-bremen",
      "canonical_url": "https://tarjetarojaenvivo.live/eventos/bundesliga/2025-12-20/fca-svw",
      "meta": {
        "title": "FC Augsburg vs. Werder Bremen EN VIVO - Tarjeta Roja TV",
        "description": "Ver FC Augsburg vs. Werder Bremen en vivo gratis el sábado 20 de diciembre de 2025",
        "keywords": "rojadirecta, tarjeta roja, rojadirecta tv, pirlotv, tarjeta roja tv, rojadirecta en vivo, tarjeta roja directa, tarjeta roja en vivo, pirlo tv rojadirecta, roja directa pirlo, tarjeta roja futbol en vivo, roja directa en vivo fútbol gratis, tarjeta roja fútbol en vivo, pirlo tv tarjeta roja, tarjeta roja tv en vivo, roja tv, la roja directa, rojadirecta tv en vivo, roja dirécta, FC Augsburg vs. Werder Bremen, Fútbol"
      },
      "event": {
        "start_time": "2025-12-20T14:30:00.000Z",
        "end_time": "2025-12-20T17:00:00.000Z",
        "status": "próximamente"
      },
      "technical": {
        "last_modified": "2025-12-20T02:01:01.197Z",
        "changefreq": "hourly",
        "priority": 0.85
      }
    },
    {
      "id": 15016,
      "slug": "fc-cologne-vs-1-fc-union-berlin",
      "canonical_url": "https://tarjetarojaenvivo.live/eventos/bundesliga/2025-12-20/koe-fcu",
      "meta": {
        "title": "FC Cologne vs. 1. FC Union Berlin EN VIVO - Tarjeta Roja TV",
        "description": "Ver FC Cologne vs. 1. FC Union Berlin en vivo gratis el sábado 20 de diciembre de 2025",
        "keywords": "rojadirecta, tarjeta roja, rojadirecta tv, pirlotv, tarjeta roja tv, rojadirecta en vivo, tarjeta roja directa, tarjeta roja en vivo, pirlo tv rojadirecta, roja directa pirlo, tarjeta roja futbol en vivo, roja directa en vivo fútbol gratis, tarjeta roja fútbol en vivo, pirlo tv tarjeta roja, tarjeta roja tv en vivo, roja tv, la roja directa, rojadirecta tv en vivo, roja dirécta, FC Cologne vs. 1. FC Union Berlin, Fútbol"
      },
      "event": {
        "start_time": "2025-12-20T14:30:00.000Z",
        "end_time": "2025-12-20T17:00:00.000Z",
        "status": "próximamente"
      },
      "technical": {
        "last_modified": "2025-12-20T02:01:01.197Z",
        "changefreq": "hourly",
        "priority": 0.85
      }
    },
    {
      "id": 15017,
      "slug": "hamburg-sv-vs-eintracht-frankfurt",
      "canonical_url": "https://tarjetarojaenvivo.live/eventos/bundesliga/2025-12-20/hsv-sge",
      "meta": {
        "title": "Hamburg SV vs. Eintracht Frankfurt EN VIVO - Tarjeta Roja TV",
        "description": "Ver Hamburg SV vs. Eintracht Frankfurt en vivo gratis el sábado 20 de diciembre de 2025",
        "keywords": "rojadirecta, tarjeta roja, rojadirecta tv, pirlotv, tarjeta roja tv, rojadirecta en vivo, tarjeta roja directa, tarjeta roja en vivo, pirlo tv rojadirecta, roja directa pirlo, tarjeta roja futbol en vivo, roja directa en vivo fútbol gratis, tarjeta roja fútbol en vivo, pirlo tv tarjeta roja, tarjeta roja tv en vivo, roja tv, la roja directa, rojadirecta tv en vivo, roja dirécta, Hamburg SV vs. Eintracht Frankfurt, Fútbol"
      },
      "event": {
        "start_time": "2025-12-20T14:30:00.000Z",
        "end_time": "2025-12-20T17:00:00.000Z",
        "status": "próximamente"
      },
      "technical": {
        "last_modified": "2025-12-20T02:01:01.197Z",
        "changefreq": "hourly",
        "priority": 0.85
      }
    },
    {
      "id": 15018,
      "slug": "vfb-stuttgart-vs-tsg-hoffenheim",
      "canonical_url": "https://tarjetarojaenvivo.live/eventos/bundesliga/2025-12-20/vfb-tsg",
      "meta": {
        "title": "VfB Stuttgart vs. TSG Hoffenheim EN VIVO - Tarjeta Roja TV",
        "description": "Ver VfB Stuttgart vs. TSG Hoffenheim en vivo gratis el sábado 20 de diciembre de 2025",
        "keywords": "rojadirecta, tarjeta roja, rojadirecta tv, pirlotv, tarjeta roja tv, rojadirecta en vivo, tarjeta roja directa, tarjeta roja en vivo, pirlo tv rojadirecta, roja directa pirlo, tarjeta roja futbol en vivo, roja directa en vivo fútbol gratis, tarjeta roja fútbol en vivo, pirlo tv tarjeta roja, tarjeta roja tv en vivo, roja tv, la roja directa, rojadirecta tv en vivo, roja dirécta, VfB Stuttgart vs. TSG Hoffenheim, Fútbol"
      },
      "event": {
        "start_time": "2025-12-20T14:30:00.000Z",
        "end_time": "2025-12-20T17:00:00.000Z",
        "status": "próximamente"
      },
      "technical": {
        "last_modified": "2025-12-20T02:01:01.197Z",
        "changefreq": "hourly",
        "priority": 0.85
      }
    },
    {
      "id": 15019,
      "slug": "vfl-wolfsburg-vs-sc-freiburg",
      "canonical_url": "https://tarjetarojaenvivo.live/eventos/bundesliga/2025-12-20/wob-scf",
      "meta": {
        "title": "VfL Wolfsburg vs. SC Freiburg EN VIVO - Tarjeta Roja TV",
        "description": "Ver VfL Wolfsburg vs. SC Freiburg en vivo gratis el sábado 20 de diciembre de 2025",
        "keywords": "rojadirecta, tarjeta roja, rojadirecta tv, pirlotv, tarjeta roja tv, rojadirecta en vivo, tarjeta roja directa, tarjeta roja en vivo, pirlo tv rojadirecta, roja directa pirlo, tarjeta roja futbol en vivo, roja directa en vivo fútbol gratis, tarjeta roja fútbol en vivo, pirlo tv tarjeta roja, tarjeta roja tv en vivo, roja tv, la roja directa, rojadirecta tv en vivo, roja dirécta, VfL Wolfsburg vs. SC Freiburg, Fútbol"
      },
      "event": {
        "start_time": "2025-12-20T14:30:00.000Z",
        "end_time": "2025-12-20T17:00:00.000Z",
        "status": "próximamente"
      },
      "technical": {
        "last_modified": "2025-12-20T02:01:01.197Z",
        "changefreq": "hourly",
        "priority": 0.85
      }
    },
    {
      "id": 5193,
      "slug": "goal-rush",
      "canonical_url": "https://tarjetarojaenvivo.live/eventos/premierleague/goal-rush",
      "meta": {
        "title": "Goal Rush EN VIVO - Tarjeta Roja TV",
        "description": "Ver Goal Rush en vivo gratis el sábado 20 de diciembre de 2025",
        "keywords": "rojadirecta, tarjeta roja, rojadirecta tv, pirlotv, tarjeta roja tv, rojadirecta en vivo, tarjeta roja directa, tarjeta roja en vivo, pirlo tv rojadirecta, roja directa pirlo, tarjeta roja futbol en vivo, roja directa en vivo fútbol gratis, tarjeta roja fútbol en vivo, pirlo tv tarjeta roja, tarjeta roja tv en vivo, roja tv, la roja directa, rojadirecta tv en vivo, roja dirécta, Goal Rush, Fútbol"
      },
      "event": {
        "start_time": "2025-12-20T15:00:00.000Z",
        "end_time": "2025-12-20T17:30:00.000Z",
        "status": "próximamente"
      },
      "technical": {
        "last_modified": "2025-12-20T02:01:01.197Z",
        "changefreq": "hourly",
        "priority": 0.85
      }
    },
    {
      "id": 15024,
      "slug": "afc-bournemouth-vs-burnley",
      "canonical_url": "https://tarjetarojaenvivo.live/eventos/premierleague/2025-12-20/bou-bur",
      "meta": {
        "title": "AFC Bournemouth vs. Burnley EN VIVO - Tarjeta Roja TV",
        "description": "Ver AFC Bournemouth vs. Burnley en vivo gratis el sábado 20 de diciembre de 2025",
        "keywords": "rojadirecta, tarjeta roja, rojadirecta tv, pirlotv, tarjeta roja tv, rojadirecta en vivo, tarjeta roja directa, tarjeta roja en vivo, pirlo tv rojadirecta, roja directa pirlo, tarjeta roja futbol en vivo, roja directa en vivo fútbol gratis, tarjeta roja fútbol en vivo, pirlo tv tarjeta roja, tarjeta roja tv en vivo, roja tv, la roja directa, rojadirecta tv en vivo, roja dirécta, AFC Bournemouth vs. Burnley, Fútbol"
      },
      "event": {
        "start_time": "2025-12-20T15:00:00.000Z",
        "end_time": "2025-12-20T17:30:00.000Z",
        "status": "próximamente"
      },
      "technical": {
        "last_modified": "2025-12-20T02:01:01.197Z",
        "changefreq": "hourly",
        "priority": 0.85
      }
    },
    {
      "id": 15025,
      "slug": "brighton-hove-albion-vs-sunderland",
      "canonical_url": "https://tarjetarojaenvivo.live/eventos/premierleague/2025-12-20/bha-sun",
      "meta": {
        "title": "Brighton & Hove Albion vs. Sunderland EN VIVO - Tarjeta Roja TV",
        "description": "Ver Brighton & Hove Albion vs. Sunderland en vivo gratis el sábado 20 de diciembre de 2025",
        "keywords": "rojadirecta, tarjeta roja, rojadirecta tv, pirlotv, tarjeta roja tv, rojadirecta en vivo, tarjeta roja directa, tarjeta roja en vivo, pirlo tv rojadirecta, roja directa pirlo, tarjeta roja futbol en vivo, roja directa en vivo fútbol gratis, tarjeta roja fútbol en vivo, pirlo tv tarjeta roja, tarjeta roja tv en vivo, roja tv, la roja directa, rojadirecta tv en vivo, roja dirécta, Brighton & Hove Albion vs. Sunderland, Fútbol"
      },
      "event": {
        "start_time": "2025-12-20T15:00:00.000Z",
        "end_time": "2025-12-20T17:30:00.000Z",
        "status": "próximamente"
      },
      "technical": {
        "last_modified": "2025-12-20T02:01:01.197Z",
        "changefreq": "hourly",
        "priority": 0.85
      }
    },
    {
      "id": 15026,
      "slug": "manchester-city-vs-west-ham-united",
      "canonical_url": "https://tarjetarojaenvivo.live/eventos/premierleague/2025-12-20/mnc-whu",
      "meta": {
        "title": "Manchester City vs. West Ham United EN VIVO - Tarjeta Roja TV",
        "description": "Ver Manchester City vs. West Ham United en vivo gratis el sábado 20 de diciembre de 2025",
        "keywords": "rojadirecta, tarjeta roja, rojadirecta tv, pirlotv, tarjeta roja tv, rojadirecta en vivo, tarjeta roja directa, tarjeta roja en vivo, pirlo tv rojadirecta, roja directa pirlo, tarjeta roja futbol en vivo, roja directa en vivo fútbol gratis, tarjeta roja fútbol en vivo, pirlo tv tarjeta roja, tarjeta roja tv en vivo, roja tv, la roja directa, rojadirecta tv en vivo, roja dirécta, Manchester City vs. West Ham United, Fútbol"
      },
      "event": {
        "start_time": "2025-12-20T15:00:00.000Z",
        "end_time": "2025-12-20T17:30:00.000Z",
        "status": "próximamente"
      },
      "technical": {
        "last_modified": "2025-12-20T02:01:01.197Z",
        "changefreq": "hourly",
        "priority": 0.85
      }
    },
    {
      "id": 15027,
      "slug": "wolverhampton-wanderers-vs-brentford",
      "canonical_url": "https://tarjetarojaenvivo.live/eventos/premierleague/2025-12-20/wol-bre",
      "meta": {
        "title": "Wolverhampton Wanderers vs. Brentford EN VIVO - Tarjeta Roja TV",
        "description": "Ver Wolverhampton Wanderers vs. Brentford en vivo gratis el sábado 20 de diciembre de 2025",
        "keywords": "rojadirecta, tarjeta roja, rojadirecta tv, pirlotv, tarjeta roja tv, rojadirecta en vivo, tarjeta roja directa, tarjeta roja en vivo, pirlo tv rojadirecta, roja directa pirlo, tarjeta roja futbol en vivo, roja directa en vivo fútbol gratis, tarjeta roja fútbol en vivo, pirlo tv tarjeta roja, tarjeta roja tv en vivo, roja tv, la roja directa, rojadirecta tv en vivo, roja dirécta, Wolverhampton Wanderers vs. Brentford, Fútbol"
      },
      "event": {
        "start_time": "2025-12-20T15:00:00.000Z",
        "end_time": "2025-12-20T17:30:00.000Z",
        "status": "próximamente"
      },
      "technical": {
        "last_modified": "2025-12-20T02:01:01.197Z",
        "changefreq": "hourly",
        "priority": 0.85
      }
    },
    {
      "id": 15006,
      "slug": "levante-vs-real-sociedad",
      "canonical_url": "https://tarjetarojaenvivo.live/eventos/laliga/2025-12-20/lev-rso",
      "meta": {
        "title": "Levante vs. Real Sociedad EN VIVO - Tarjeta Roja TV",
        "description": "Ver Levante vs. Real Sociedad en vivo gratis el sábado 20 de diciembre de 2025",
        "keywords": "rojadirecta, tarjeta roja, rojadirecta tv, pirlotv, tarjeta roja tv, rojadirecta en vivo, tarjeta roja directa, tarjeta roja en vivo, pirlo tv rojadirecta, roja directa pirlo, tarjeta roja futbol en vivo, roja directa en vivo fútbol gratis, tarjeta roja fútbol en vivo, pirlo tv tarjeta roja, tarjeta roja tv en vivo, roja tv, la roja directa, rojadirecta tv en vivo, roja dirécta, Levante vs. Real Sociedad, Fútbol"
      },
      "event": {
        "start_time": "2025-12-20T15:15:00.000Z",
        "end_time": "2025-12-20T17:45:00.000Z",
        "status": "próximamente"
      },
      "technical": {
        "last_modified": "2025-12-20T02:01:01.197Z",
        "changefreq": "hourly",
        "priority": 0.85
      }
    },
    {
      "id": 15034,
      "slug": "lazio-vs-cremonese",
      "canonical_url": "https://tarjetarojaenvivo.live/eventos/seriea/2025-12-20/laz-cre",
      "meta": {
        "title": "Lazio vs. Cremonese EN VIVO - Tarjeta Roja TV",
        "description": "Ver Lazio vs. Cremonese en vivo gratis el sábado 20 de diciembre de 2025",
        "keywords": "rojadirecta, tarjeta roja, rojadirecta tv, pirlotv, tarjeta roja tv, rojadirecta en vivo, tarjeta roja directa, tarjeta roja en vivo, pirlo tv rojadirecta, roja directa pirlo, tarjeta roja futbol en vivo, roja directa en vivo fútbol gratis, tarjeta roja fútbol en vivo, pirlo tv tarjeta roja, tarjeta roja tv en vivo, roja tv, la roja directa, rojadirecta tv en vivo, roja dirécta, Lazio vs. Cremonese, Fútbol"
      },
      "event": {
        "start_time": "2025-12-20T17:00:00.000Z",
        "end_time": "2025-12-20T19:30:00.000Z",
        "status": "próximamente"
      },
      "technical": {
        "last_modified": "2025-12-20T02:01:01.197Z",
        "changefreq": "hourly",
        "priority": 0.85
      }
    },
    {
      "id": 15007,
      "slug": "osasuna-vs-alaves",
      "canonical_url": "https://tarjetarojaenvivo.live/eventos/laliga/2025-12-20/osa-ala",
      "meta": {
        "title": "Osasuna vs. Alavés EN VIVO - Tarjeta Roja TV",
        "description": "Ver Osasuna vs. Alavés en vivo gratis el sábado 20 de diciembre de 2025",
        "keywords": "rojadirecta, tarjeta roja, rojadirecta tv, pirlotv, tarjeta roja tv, rojadirecta en vivo, tarjeta roja directa, tarjeta roja en vivo, pirlo tv rojadirecta, roja directa pirlo, tarjeta roja futbol en vivo, roja directa en vivo fútbol gratis, tarjeta roja fútbol en vivo, pirlo tv tarjeta roja, tarjeta roja tv en vivo, roja tv, la roja directa, rojadirecta tv en vivo, roja dirécta, Osasuna vs. Alavés, Fútbol"
      },
      "event": {
        "start_time": "2025-12-20T17:30:00.000Z",
        "end_time": "2025-12-20T20:00:00.000Z",
        "status": "próximamente"
      },
      "technical": {
        "last_modified": "2025-12-20T02:01:01.197Z",
        "changefreq": "hourly",
        "priority": 0.85
      }
    },
    {
      "id": 15020,
      "slug": "rb-leipzig-vs-bayer-leverkusen",
      "canonical_url": "https://tarjetarojaenvivo.live/eventos/bundesliga/2025-12-20/rbl-b04",
      "meta": {
        "title": "RB Leipzig vs. Bayer Leverkusen EN VIVO - Tarjeta Roja TV",
        "description": "Ver RB Leipzig vs. Bayer Leverkusen en vivo gratis el sábado 20 de diciembre de 2025",
        "keywords": "rojadirecta, tarjeta roja, rojadirecta tv, pirlotv, tarjeta roja tv, rojadirecta en vivo, tarjeta roja directa, tarjeta roja en vivo, pirlo tv rojadirecta, roja directa pirlo, tarjeta roja futbol en vivo, roja directa en vivo fútbol gratis, tarjeta roja fútbol en vivo, pirlo tv tarjeta roja, tarjeta roja tv en vivo, roja tv, la roja directa, rojadirecta tv en vivo, roja dirécta, RB Leipzig vs. Bayer Leverkusen, Fútbol"
      },
      "event": {
        "start_time": "2025-12-20T17:30:00.000Z",
        "end_time": "2025-12-20T20:00:00.000Z",
        "status": "próximamente"
      },
      "technical": {
        "last_modified": "2025-12-20T02:01:01.197Z",
        "changefreq": "hourly",
        "priority": 0.85
      }
    },
    {
      "id": 15028,
      "slug": "tottenham-hotspur-vs-liverpool",
      "canonical_url": "https://tarjetarojaenvivo.live/eventos/premierleague/2025-12-20/tot-liv",
      "meta": {
        "title": "Tottenham Hotspur vs. Liverpool EN VIVO - Tarjeta Roja TV",
        "description": "Ver Tottenham Hotspur vs. Liverpool en vivo gratis el sábado 20 de diciembre de 2025",
        "keywords": "rojadirecta, tarjeta roja, rojadirecta tv, pirlotv, tarjeta roja tv, rojadirecta en vivo, tarjeta roja directa, tarjeta roja en vivo, pirlo tv rojadirecta, roja directa pirlo, tarjeta roja futbol en vivo, roja directa en vivo fútbol gratis, tarjeta roja fútbol en vivo, pirlo tv tarjeta roja, tarjeta roja tv en vivo, roja tv, la roja directa, rojadirecta tv en vivo, roja dirécta, Tottenham Hotspur vs. Liverpool, Fútbol"
      },
      "event": {
        "start_time": "2025-12-20T17:30:00.000Z",
        "end_time": "2025-12-20T20:00:00.000Z",
        "status": "próximamente"
      },
      "technical": {
        "last_modified": "2025-12-20T02:01:01.197Z",
        "changefreq": "hourly",
        "priority": 0.85
      }
    },
    {
      "id": 15035,
      "slug": "juventus-vs-as-roma",
      "canonical_url": "https://tarjetarojaenvivo.live/eventos/seriea/2025-12-20/juv-roma",
      "meta": {
        "title": "Juventus vs. AS Roma EN VIVO - Tarjeta Roja TV",
        "description": "Ver Juventus vs. AS Roma en vivo gratis el sábado 20 de diciembre de 2025",
        "keywords": "rojadirecta, tarjeta roja, rojadirecta tv, pirlotv, tarjeta roja tv, rojadirecta en vivo, tarjeta roja directa, tarjeta roja en vivo, pirlo tv rojadirecta, roja directa pirlo, tarjeta roja futbol en vivo, roja directa en vivo fútbol gratis, tarjeta roja fútbol en vivo, pirlo tv tarjeta roja, tarjeta roja tv en vivo, roja tv, la roja directa, rojadirecta tv en vivo, roja dirécta, Juventus vs. AS Roma, Fútbol"
      },
      "event": {
        "start_time": "2025-12-20T19:45:00.000Z",
        "end_time": "2025-12-20T22:15:00.000Z",
        "status": "próximamente"
      },
      "technical": {
        "last_modified": "2025-12-20T02:01:01.197Z",
        "changefreq": "hourly",
        "priority": 0.85
      }
    },
    {
      "id": 15008,
      "slug": "real-madrid-vs-sevilla",
      "canonical_url": "https://tarjetarojaenvivo.live/eventos/laliga/2025-12-20/rma-sev",
      "meta": {
        "title": "Real Madrid vs. Sevilla EN VIVO - Tarjeta Roja TV",
        "description": "Ver Real Madrid vs. Sevilla en vivo gratis el sábado 20 de diciembre de 2025",
        "keywords": "rojadirecta, tarjeta roja, rojadirecta tv, pirlotv, tarjeta roja tv, rojadirecta en vivo, tarjeta roja directa, tarjeta roja en vivo, pirlo tv rojadirecta, roja directa pirlo, tarjeta roja futbol en vivo, roja directa en vivo fútbol gratis, tarjeta roja fútbol en vivo, pirlo tv tarjeta roja, tarjeta roja tv en vivo, roja tv, la roja directa, rojadirecta tv en vivo, roja dirécta, Real Madrid vs. Sevilla, Fútbol"
      },
      "event": {
        "start_time": "2025-12-20T20:00:00.000Z",
        "end_time": "2025-12-20T22:30:00.000Z",
        "status": "próximamente"
      },
      "technical": {
        "last_modified": "2025-12-20T02:01:01.197Z",
        "changefreq": "hourly",
        "priority": 0.85
      }
    },
    {
      "id": 15029,
      "slug": "everton-vs-arsenal",
      "canonical_url": "https://tarjetarojaenvivo.live/eventos/premierleague/2025-12-20/eve-ars",
      "meta": {
        "title": "Everton vs. Arsenal EN VIVO - Tarjeta Roja TV",
        "description": "Ver Everton vs. Arsenal en vivo gratis el sábado 20 de diciembre de 2025",
        "keywords": "rojadirecta, tarjeta roja, rojadirecta tv, pirlotv, tarjeta roja tv, rojadirecta en vivo, tarjeta roja directa, tarjeta roja en vivo, pirlo tv rojadirecta, roja directa pirlo, tarjeta roja futbol en vivo, roja directa en vivo fútbol gratis, tarjeta roja fútbol en vivo, pirlo tv tarjeta roja, tarjeta roja tv en vivo, roja tv, la roja directa, rojadirecta tv en vivo, roja dirécta, Everton vs. Arsenal, Fútbol"
      },
      "event": {
        "start_time": "2025-12-20T20:00:00.000Z",
        "end_time": "2025-12-20T22:30:00.000Z",
        "status": "próximamente"
      },
      "technical": {
        "last_modified": "2025-12-20T02:01:01.197Z",
        "changefreq": "hourly",
        "priority": 0.85
      }
    },
    {
      "id": 15030,
      "slug": "leeds-united-vs-crystal-palace",
      "canonical_url": "https://tarjetarojaenvivo.live/eventos/premierleague/2025-12-20/lee-cry",
      "meta": {
        "title": "Leeds United vs. Crystal Palace EN VIVO - Tarjeta Roja TV",
        "description": "Ver Leeds United vs. Crystal Palace en vivo gratis el sábado 20 de diciembre de 2025",
        "keywords": "rojadirecta, tarjeta roja, rojadirecta tv, pirlotv, tarjeta roja tv, rojadirecta en vivo, tarjeta roja directa, tarjeta roja en vivo, pirlo tv rojadirecta, roja directa pirlo, tarjeta roja futbol en vivo, roja directa en vivo fútbol gratis, tarjeta roja fútbol en vivo, pirlo tv tarjeta roja, tarjeta roja tv en vivo, roja tv, la roja directa, rojadirecta tv en vivo, roja dirécta, Leeds United vs. Crystal Palace, Fútbol"
      },
      "event": {
        "start_time": "2025-12-20T20:00:00.000Z",
        "end_time": "2025-12-20T22:30:00.000Z",
        "status": "próximamente"
      },
      "technical": {
        "last_modified": "2025-12-20T02:01:01.197Z",
        "changefreq": "hourly",
        "priority": 0.85
      }
    },
    {
      "id": 15036,
      "slug": "cagliari-vs-pisa",
      "canonical_url": "https://tarjetarojaenvivo.live/eventos/seriea/2025-12-21/cag-pis",
      "meta": {
        "title": "Cagliari vs. Pisa EN VIVO - Tarjeta Roja TV",
        "description": "Ver Cagliari vs. Pisa en vivo gratis el domingo 21 de diciembre de 2025",
        "keywords": "rojadirecta, tarjeta roja, rojadirecta tv, pirlotv, tarjeta roja tv, rojadirecta en vivo, tarjeta roja directa, tarjeta roja en vivo, pirlo tv rojadirecta, roja directa pirlo, tarjeta roja futbol en vivo, roja directa en vivo fútbol gratis, tarjeta roja fútbol en vivo, pirlo tv tarjeta roja, tarjeta roja tv en vivo, roja tv, la roja directa, rojadirecta tv en vivo, roja dirécta, Cagliari vs. Pisa, Fútbol"
      },
      "event": {
        "start_time": "2025-12-21T11:30:00.000Z",
        "end_time": "2025-12-21T14:00:00.000Z",
        "status": "próximamente"
      },
      "technical": {
        "last_modified": "2025-12-20T02:01:01.197Z",
        "changefreq": "hourly",
        "priority": 0.85
      }
    },
    {
      "id": 15009,
      "slug": "girona-vs-atletico-madrid",
      "canonical_url": "https://tarjetarojaenvivo.live/eventos/laliga/2025-12-21/gir-atm",
      "meta": {
        "title": "Girona vs. Atlético Madrid EN VIVO - Tarjeta Roja TV",
        "description": "Ver Girona vs. Atlético Madrid en vivo gratis el domingo 21 de diciembre de 2025",
        "keywords": "rojadirecta, tarjeta roja, rojadirecta tv, pirlotv, tarjeta roja tv, rojadirecta en vivo, tarjeta roja directa, tarjeta roja en vivo, pirlo tv rojadirecta, roja directa pirlo, tarjeta roja futbol en vivo, roja directa en vivo fútbol gratis, tarjeta roja fútbol en vivo, pirlo tv tarjeta roja, tarjeta roja tv en vivo, roja tv, la roja directa, rojadirecta tv en vivo, roja dirécta, Girona vs. Atlético Madrid, Fútbol"
      },
      "event": {
        "start_time": "2025-12-21T13:00:00.000Z",
        "end_time": "2025-12-21T15:30:00.000Z",
        "status": "próximamente"
      },
      "technical": {
        "last_modified": "2025-12-20T02:01:01.197Z",
        "changefreq": "hourly",
        "priority": 0.85
      }
    },
    {
      "id": 15037,
      "slug": "sassuolo-vs-torino",
      "canonical_url": "https://tarjetarojaenvivo.live/eventos/seriea/2025-12-21/sas-tor",
      "meta": {
        "title": "Sassuolo vs. Torino EN VIVO - Tarjeta Roja TV",
        "description": "Ver Sassuolo vs. Torino en vivo gratis el domingo 21 de diciembre de 2025",
        "keywords": "rojadirecta, tarjeta roja, rojadirecta tv, pirlotv, tarjeta roja tv, rojadirecta en vivo, tarjeta roja directa, tarjeta roja en vivo, pirlo tv rojadirecta, roja directa pirlo, tarjeta roja futbol en vivo, roja directa en vivo fútbol gratis, tarjeta roja fútbol en vivo, pirlo tv tarjeta roja, tarjeta roja tv en vivo, roja tv, la roja directa, rojadirecta tv en vivo, roja dirécta, Sassuolo vs. Torino, Fútbol"
      },
      "event": {
        "start_time": "2025-12-21T14:00:00.000Z",
        "end_time": "2025-12-21T16:30:00.000Z",
        "status": "próximamente"
      },
      "technical": {
        "last_modified": "2025-12-20T02:01:01.197Z",
        "changefreq": "hourly",
        "priority": 0.85
      }
    },
    {
      "id": 15021,
      "slug": "mainz-vs-st-pauli",
      "canonical_url": "https://tarjetarojaenvivo.live/eventos/bundesliga/2025-12-21/m05-stp",
      "meta": {
        "title": "Mainz vs. St. Pauli EN VIVO - Tarjeta Roja TV",
        "description": "Ver Mainz vs. St. Pauli en vivo gratis el domingo 21 de diciembre de 2025",
        "keywords": "rojadirecta, tarjeta roja, rojadirecta tv, pirlotv, tarjeta roja tv, rojadirecta en vivo, tarjeta roja directa, tarjeta roja en vivo, pirlo tv rojadirecta, roja directa pirlo, tarjeta roja futbol en vivo, roja directa en vivo fútbol gratis, tarjeta roja fútbol en vivo, pirlo tv tarjeta roja, tarjeta roja tv en vivo, roja tv, la roja directa, rojadirecta tv en vivo, roja dirécta, Mainz vs. St. Pauli, Fútbol"
      },
      "event": {
        "start_time": "2025-12-21T14:30:00.000Z",
        "end_time": "2025-12-21T17:00:00.000Z",
        "status": "próximamente"
      },
      "technical": {
        "last_modified": "2025-12-20T02:01:01.197Z",
        "changefreq": "hourly",
        "priority": 0.85
      }
    },
    {
      "id": 15010,
      "slug": "villarreal-vs-barcelona",
      "canonical_url": "https://tarjetarojaenvivo.live/eventos/laliga/2025-12-21/vil-bar",
      "meta": {
        "title": "Villarreal vs. Barcelona EN VIVO - Tarjeta Roja TV",
        "description": "Ver Villarreal vs. Barcelona en vivo gratis el domingo 21 de diciembre de 2025",
        "keywords": "rojadirecta, tarjeta roja, rojadirecta tv, pirlotv, tarjeta roja tv, rojadirecta en vivo, tarjeta roja directa, tarjeta roja en vivo, pirlo tv rojadirecta, roja directa pirlo, tarjeta roja futbol en vivo, roja directa en vivo fútbol gratis, tarjeta roja fútbol en vivo, pirlo tv tarjeta roja, tarjeta roja tv en vivo, roja tv, la roja directa, rojadirecta tv en vivo, roja dirécta, Villarreal vs. Barcelona, Fútbol"
      },
      "event": {
        "start_time": "2025-12-21T15:15:00.000Z",
        "end_time": "2025-12-21T17:45:00.000Z",
        "status": "próximamente"
      },
      "technical": {
        "last_modified": "2025-12-20T02:01:01.197Z",
        "changefreq": "hourly",
        "priority": 0.85
      }
    },
    {
      "id": 15022,
      "slug": "1-fc-heidenheim-1846-vs-bayern-munich",
      "canonical_url": "https://tarjetarojaenvivo.live/eventos/bundesliga/2025-12-21/hdh-mun",
      "meta": {
        "title": "1. FC Heidenheim 1846 vs. Bayern Munich EN VIVO - Tarjeta Roja TV",
        "description": "Ver 1. FC Heidenheim 1846 vs. Bayern Munich en vivo gratis el domingo 21 de diciembre de 2025",
        "keywords": "rojadirecta, tarjeta roja, rojadirecta tv, pirlotv, tarjeta roja tv, rojadirecta en vivo, tarjeta roja directa, tarjeta roja en vivo, pirlo tv rojadirecta, roja directa pirlo, tarjeta roja futbol en vivo, roja directa en vivo fútbol gratis, tarjeta roja fútbol en vivo, pirlo tv tarjeta roja, tarjeta roja tv en vivo, roja tv, la roja directa, rojadirecta tv en vivo, roja dirécta, 1. FC Heidenheim 1846 vs. Bayern Munich, Fútbol"
      },
      "event": {
        "start_time": "2025-12-21T16:30:00.000Z",
        "end_time": "2025-12-21T19:00:00.000Z",
        "status": "próximamente"
      },
      "technical": {
        "last_modified": "2025-12-20T02:01:01.197Z",
        "changefreq": "hourly",
        "priority": 0.85
      }
    },
    {
      "id": 15031,
      "slug": "aston-villa-vs-manchester-united",
      "canonical_url": "https://tarjetarojaenvivo.live/eventos/premierleague/2025-12-21/avl-man",
      "meta": {
        "title": "Aston Villa vs. Manchester United EN VIVO - Tarjeta Roja TV",
        "description": "Ver Aston Villa vs. Manchester United en vivo gratis el domingo 21 de diciembre de 2025",
        "keywords": "rojadirecta, tarjeta roja, rojadirecta tv, pirlotv, tarjeta roja tv, rojadirecta en vivo, tarjeta roja directa, tarjeta roja en vivo, pirlo tv rojadirecta, roja directa pirlo, tarjeta roja futbol en vivo, roja directa en vivo fútbol gratis, tarjeta roja fútbol en vivo, pirlo tv tarjeta roja, tarjeta roja tv en vivo, roja tv, la roja directa, rojadirecta tv en vivo, roja dirécta, Aston Villa vs. Manchester United, Fútbol"
      },
      "event": {
        "start_time": "2025-12-21T16:30:00.000Z",
        "end_time": "2025-12-21T19:00:00.000Z",
        "status": "próximamente"
      },
      "technical": {
        "last_modified": "2025-12-20T02:01:01.197Z",
        "changefreq": "hourly",
        "priority": 0.85
      }
    },
    {
      "id": 15038,
      "slug": "fiorentina-vs-udinese",
      "canonical_url": "https://tarjetarojaenvivo.live/eventos/seriea/2025-12-21/fio-udi",
      "meta": {
        "title": "Fiorentina vs. Udinese EN VIVO - Tarjeta Roja TV",
        "description": "Ver Fiorentina vs. Udinese en vivo gratis el domingo 21 de diciembre de 2025",
        "keywords": "rojadirecta, tarjeta roja, rojadirecta tv, pirlotv, tarjeta roja tv, rojadirecta en vivo, tarjeta roja directa, tarjeta roja en vivo, pirlo tv rojadirecta, roja directa pirlo, tarjeta roja futbol en vivo, roja directa en vivo fútbol gratis, tarjeta roja fútbol en vivo, pirlo tv tarjeta roja, tarjeta roja tv en vivo, roja tv, la roja directa, rojadirecta tv en vivo, roja dirécta, Fiorentina vs. Udinese, Fútbol"
      },
      "event": {
        "start_time": "2025-12-21T17:00:00.000Z",
        "end_time": "2025-12-21T19:30:00.000Z",
        "status": "próximamente"
      },
      "technical": {
        "last_modified": "2025-12-20T02:01:01.197Z",
        "changefreq": "hourly",
        "priority": 0.85
      }
    },
    {
      "id": 15011,
      "slug": "elche-vs-rayo-vallecano",
      "canonical_url": "https://tarjetarojaenvivo.live/eventos/laliga/2025-12-21/elc-ray",
      "meta": {
        "title": "Elche vs. Rayo Vallecano EN VIVO - Tarjeta Roja TV",
        "description": "Ver Elche vs. Rayo Vallecano en vivo gratis el domingo 21 de diciembre de 2025",
        "keywords": "rojadirecta, tarjeta roja, rojadirecta tv, pirlotv, tarjeta roja tv, rojadirecta en vivo, tarjeta roja directa, tarjeta roja en vivo, pirlo tv rojadirecta, roja directa pirlo, tarjeta roja futbol en vivo, roja directa en vivo fútbol gratis, tarjeta roja fútbol en vivo, pirlo tv tarjeta roja, tarjeta roja tv en vivo, roja tv, la roja directa, rojadirecta tv en vivo, roja dirécta, Elche vs. Rayo Vallecano, Fútbol"
      },
      "event": {
        "start_time": "2025-12-21T17:30:00.000Z",
        "end_time": "2025-12-21T20:00:00.000Z",
        "status": "próximamente"
      },
      "technical": {
        "last_modified": "2025-12-20T02:01:01.197Z",
        "changefreq": "hourly",
        "priority": 0.85
      }
    },
    {
      "id": 15039,
      "slug": "genoa-vs-atalanta",
      "canonical_url": "https://tarjetarojaenvivo.live/eventos/seriea/2025-12-21/gen-ata",
      "meta": {
        "title": "Genoa vs. Atalanta EN VIVO - Tarjeta Roja TV",
        "description": "Ver Genoa vs. Atalanta en vivo gratis el domingo 21 de diciembre de 2025",
        "keywords": "rojadirecta, tarjeta roja, rojadirecta tv, pirlotv, tarjeta roja tv, rojadirecta en vivo, tarjeta roja directa, tarjeta roja en vivo, pirlo tv rojadirecta, roja directa pirlo, tarjeta roja futbol en vivo, roja directa en vivo fútbol gratis, tarjeta roja fútbol en vivo, pirlo tv tarjeta roja, tarjeta roja tv en vivo, roja tv, la roja directa, rojadirecta tv en vivo, roja dirécta, Genoa vs. Atalanta, Fútbol"
      },
      "event": {
        "start_time": "2025-12-21T19:45:00.000Z",
        "end_time": "2025-12-21T22:15:00.000Z",
        "status": "próximamente"
      },
      "technical": {
        "last_modified": "2025-12-20T02:01:01.197Z",
        "changefreq": "hourly",
        "priority": 0.85
      }
    },
    {
      "id": 15012,
      "slug": "real-betis-vs-getafe",
      "canonical_url": "https://tarjetarojaenvivo.live/eventos/laliga/2025-12-21/bet-get",
      "meta": {
        "title": "Real Betis vs. Getafe EN VIVO - Tarjeta Roja TV",
        "description": "Ver Real Betis vs. Getafe en vivo gratis el domingo 21 de diciembre de 2025",
        "keywords": "rojadirecta, tarjeta roja, rojadirecta tv, pirlotv, tarjeta roja tv, rojadirecta en vivo, tarjeta roja directa, tarjeta roja en vivo, pirlo tv rojadirecta, roja directa pirlo, tarjeta roja futbol en vivo, roja directa en vivo fútbol gratis, tarjeta roja fútbol en vivo, pirlo tv tarjeta roja, tarjeta roja tv en vivo, roja tv, la roja directa, rojadirecta tv en vivo, roja dirécta, Real Betis vs. Getafe, Fútbol"
      },
      "event": {
        "start_time": "2025-12-21T20:00:00.000Z",
        "end_time": "2025-12-21T22:30:00.000Z",
        "status": "próximamente"
      },
      "technical": {
        "last_modified": "2025-12-20T02:01:01.197Z",
        "changefreq": "hourly",
        "priority": 0.85
      }
    },
    {
      "id": 15013,
      "slug": "athletic-club-vs-espanyol",
      "canonical_url": "https://tarjetarojaenvivo.live/eventos/laliga/2025-12-22/ath-esp",
      "meta": {
        "title": "Athletic Club vs. Espanyol EN VIVO - Tarjeta Roja TV",
        "description": "Ver Athletic Club vs. Espanyol en vivo gratis el lunes 22 de diciembre de 2025",
        "keywords": "rojadirecta, tarjeta roja, rojadirecta tv, pirlotv, tarjeta roja tv, rojadirecta en vivo, tarjeta roja directa, tarjeta roja en vivo, pirlo tv rojadirecta, roja directa pirlo, tarjeta roja futbol en vivo, roja directa en vivo fútbol gratis, tarjeta roja fútbol en vivo, pirlo tv tarjeta roja, tarjeta roja tv en vivo, roja tv, la roja directa, rojadirecta tv en vivo, roja dirécta, Athletic Club vs. Espanyol, Fútbol"
      },
      "event": {
        "start_time": "2025-12-22T20:00:00.000Z",
        "end_time": "2025-12-22T22:30:00.000Z",
        "status": "próximamente"
      },
      "technical": {
        "last_modified": "2025-12-20T02:01:01.197Z",
        "changefreq": "hourly",
        "priority": 0.85
      }
    },
    {
      "id": 15032,
      "slug": "fulham-vs-nottingham-forest",
      "canonical_url": "https://tarjetarojaenvivo.live/eventos/premierleague/2025-12-22/ful-nfo",
      "meta": {
        "title": "Fulham vs. Nottingham Forest EN VIVO - Tarjeta Roja TV",
        "description": "Ver Fulham vs. Nottingham Forest en vivo gratis el lunes 22 de diciembre de 2025",
        "keywords": "rojadirecta, tarjeta roja, rojadirecta tv, pirlotv, tarjeta roja tv, rojadirecta en vivo, tarjeta roja directa, tarjeta roja en vivo, pirlo tv rojadirecta, roja directa pirlo, tarjeta roja futbol en vivo, roja directa en vivo fútbol gratis, tarjeta roja fútbol en vivo, pirlo tv tarjeta roja, tarjeta roja tv en vivo, roja tv, la roja directa, rojadirecta tv en vivo, roja dirécta, Fulham vs. Nottingham Forest, Fútbol"
      },
      "event": {
        "start_time": "2025-12-22T20:00:00.000Z",
        "end_time": "2025-12-22T22:30:00.000Z",
        "status": "próximamente"
      },
      "technical": {
        "last_modified": "2025-12-20T02:01:01.197Z",
        "changefreq": "hourly",
        "priority": 0.85
      }
    },
    {
      "id": 15168,
      "slug": "carolina-hurricanes-vs-florida-panthers",
      "canonical_url": "https://tarjetarojaenvivo.live/eventos/nhl/2025-12-19/car-fla",
      "meta": {
        "title": "Carolina Hurricanes vs. Florida Panthers EN VIVO - Tarjeta Roja TV",
        "description": "Ver Carolina Hurricanes vs. Florida Panthers en vivo gratis el sábado 20 de diciembre de 2025",
        "keywords": "rojadirecta, tarjeta roja, rojadirecta tv, pirlotv, tarjeta roja tv, rojadirecta en vivo, tarjeta roja directa, tarjeta roja en vivo, pirlo tv rojadirecta, roja directa pirlo, tarjeta roja futbol en vivo, roja directa en vivo fútbol gratis, tarjeta roja fútbol en vivo, pirlo tv tarjeta roja, tarjeta roja tv en vivo, roja tv, la roja directa, rojadirecta tv en vivo, roja dirécta, Carolina Hurricanes vs. Florida Panthers, Hockey sobre Hielo"
      },
      "event": {
        "start_time": "2025-12-20T00:00:00.000Z",
        "end_time": "2025-12-20T03:00:00.000Z",
        "status": "en vivo"
      },
      "technical": {
        "last_modified": "2025-12-20T02:01:01.197Z",
        "changefreq": "hourly",
        "priority": 0.85
      }
    },
    {
      "id": 15170,
      "slug": "vancouver-canucks-vs-new-york-islanders",
      "canonical_url": "https://tarjetarojaenvivo.live/eventos/nhl/2025-12-19/van-nyi",
      "meta": {
        "title": "Vancouver Canucks vs. New York Islanders EN VIVO - Tarjeta Roja TV",
        "description": "Ver Vancouver Canucks vs. New York Islanders en vivo gratis el sábado 20 de diciembre de 2025",
        "keywords": "rojadirecta, tarjeta roja, rojadirecta tv, pirlotv, tarjeta roja tv, rojadirecta en vivo, tarjeta roja directa, tarjeta roja en vivo, pirlo tv rojadirecta, roja directa pirlo, tarjeta roja futbol en vivo, roja directa en vivo fútbol gratis, tarjeta roja fútbol en vivo, pirlo tv tarjeta roja, tarjeta roja tv en vivo, roja tv, la roja directa, rojadirecta tv en vivo, roja dirécta, Vancouver Canucks vs. New York Islanders, Hockey sobre Hielo"
      },
      "event": {
        "start_time": "2025-12-20T00:00:00.000Z",
        "end_time": "2025-12-20T03:00:00.000Z",
        "status": "en vivo"
      },
      "technical": {
        "last_modified": "2025-12-20T02:01:01.197Z",
        "changefreq": "hourly",
        "priority": 0.85
      }
    },
    {
      "id": 15172,
      "slug": "winnipeg-jets-vs-colorado-avalanche",
      "canonical_url": "https://tarjetarojaenvivo.live/eventos/nhl/2025-12-19/wpg-col",
      "meta": {
        "title": "Winnipeg Jets vs. Colorado Avalanche EN VIVO - Tarjeta Roja TV",
        "description": "Ver Winnipeg Jets vs. Colorado Avalanche en vivo gratis el sábado 20 de diciembre de 2025",
        "keywords": "rojadirecta, tarjeta roja, rojadirecta tv, pirlotv, tarjeta roja tv, rojadirecta en vivo, tarjeta roja directa, tarjeta roja en vivo, pirlo tv rojadirecta, roja directa pirlo, tarjeta roja futbol en vivo, roja directa en vivo fútbol gratis, tarjeta roja fútbol en vivo, pirlo tv tarjeta roja, tarjeta roja tv en vivo, roja tv, la roja directa, rojadirecta tv en vivo, roja dirécta, Winnipeg Jets vs. Colorado Avalanche, Hockey sobre Hielo"
      },
      "event": {
        "start_time": "2025-12-20T02:00:00.000Z",
        "end_time": "2025-12-20T05:00:00.000Z",
        "status": "en vivo"
      },
      "technical": {
        "last_modified": "2025-12-20T02:01:01.197Z",
        "changefreq": "hourly",
        "priority": 0.85
      }
    },
    {
      "id": 15174,
      "slug": "new-jersey-devils-vs-utah-mammoth",
      "canonical_url": "https://tarjetarojaenvivo.live/eventos/nhl/2025-12-19/nj-uta",
      "meta": {
        "title": "New Jersey Devils vs. Utah Mammoth EN VIVO - Tarjeta Roja TV",
        "description": "Ver New Jersey Devils vs. Utah Mammoth en vivo gratis el sábado 20 de diciembre de 2025",
        "keywords": "rojadirecta, tarjeta roja, rojadirecta tv, pirlotv, tarjeta roja tv, rojadirecta en vivo, tarjeta roja directa, tarjeta roja en vivo, pirlo tv rojadirecta, roja directa pirlo, tarjeta roja futbol en vivo, roja directa en vivo fútbol gratis, tarjeta roja fútbol en vivo, pirlo tv tarjeta roja, tarjeta roja tv en vivo, roja tv, la roja directa, rojadirecta tv en vivo, roja dirécta, New Jersey Devils vs. Utah Mammoth, Hockey sobre Hielo"
      },
      "event": {
        "start_time": "2025-12-20T02:00:00.000Z",
        "end_time": "2025-12-20T05:00:00.000Z",
        "status": "en vivo"
      },
      "technical": {
        "last_modified": "2025-12-20T02:01:01.197Z",
        "changefreq": "hourly",
        "priority": 0.85
      }
    },
    {
      "id": 15176,
      "slug": "dallas-stars-vs-anaheim-ducks",
      "canonical_url": "https://tarjetarojaenvivo.live/eventos/nhl/2025-12-19/dal-ana",
      "meta": {
        "title": "Dallas Stars vs. Anaheim Ducks EN VIVO - Tarjeta Roja TV",
        "description": "Ver Dallas Stars vs. Anaheim Ducks en vivo gratis el sábado 20 de diciembre de 2025",
        "keywords": "rojadirecta, tarjeta roja, rojadirecta tv, pirlotv, tarjeta roja tv, rojadirecta en vivo, tarjeta roja directa, tarjeta roja en vivo, pirlo tv rojadirecta, roja directa pirlo, tarjeta roja futbol en vivo, roja directa en vivo fútbol gratis, tarjeta roja fútbol en vivo, pirlo tv tarjeta roja, tarjeta roja tv en vivo, roja tv, la roja directa, rojadirecta tv en vivo, roja dirécta, Dallas Stars vs. Anaheim Ducks, Hockey sobre Hielo"
      },
      "event": {
        "start_time": "2025-12-20T03:00:00.000Z",
        "end_time": "2025-12-20T06:00:00.000Z",
        "status": "próximamente"
      },
      "technical": {
        "last_modified": "2025-12-20T02:01:01.197Z",
        "changefreq": "hourly",
        "priority": 0.85
      }
    },
    {
      "id": 15055,
      "slug": "wwe-friday-night-smackdown",
      "canonical_url": "https://tarjetarojaenvivo.live/eventos/wwe/smackdown/2025-12-20",
      "meta": {
        "title": "WWE: Friday Night Smackdown EN VIVO - Tarjeta Roja TV",
        "description": "Ver WWE: Friday Night Smackdown en vivo gratis el sábado 20 de diciembre de 2025",
        "keywords": "rojadirecta, tarjeta roja, rojadirecta tv, pirlotv, tarjeta roja tv, rojadirecta en vivo, tarjeta roja directa, tarjeta roja en vivo, pirlo tv rojadirecta, roja directa pirlo, tarjeta roja futbol en vivo, roja directa en vivo fútbol gratis, tarjeta roja fútbol en vivo, pirlo tv tarjeta roja, tarjeta roja tv en vivo, roja tv, la roja directa, rojadirecta tv en vivo, roja dirécta, WWE: Friday Night Smackdown, Lucha Libre"
      },
      "event": {
        "start_time": "2025-12-20T01:00:00.000Z",
        "end_time": "2025-12-20T04:00:00.000Z",
        "status": "en vivo"
      },
      "technical": {
        "last_modified": "2025-12-20T02:01:01.197Z",
        "changefreq": "hourly",
        "priority": 0.85
      }
    },
    {
      "id": 15056,
      "slug": "aew-saturday-night-collision",
      "canonical_url": "https://tarjetarojaenvivo.live/eventos/aew/collision/2025-12-21",
      "meta": {
        "title": "AEW: Saturday Night Collision EN VIVO - Tarjeta Roja TV",
        "description": "Ver AEW: Saturday Night Collision en vivo gratis el domingo 21 de diciembre de 2025",
        "keywords": "rojadirecta, tarjeta roja, rojadirecta tv, pirlotv, tarjeta roja tv, rojadirecta en vivo, tarjeta roja directa, tarjeta roja en vivo, pirlo tv rojadirecta, roja directa pirlo, tarjeta roja futbol en vivo, roja directa en vivo fútbol gratis, tarjeta roja fútbol en vivo, pirlo tv tarjeta roja, tarjeta roja tv en vivo, roja tv, la roja directa, rojadirecta tv en vivo, roja dirécta, AEW: Saturday Night Collision, Lucha Libre"
      },
      "event": {
        "start_time": "2025-12-21T01:00:00.000Z",
        "end_time": "2025-12-21T04:00:00.000Z",
        "status": "próximamente"
      },
      "technical": {
        "last_modified": "2025-12-20T02:01:01.197Z",
        "changefreq": "hourly",
        "priority": 0.85
      }
    },
    {
      "id": 5112,
      "slug": "24-7-south-park",
      "canonical_url": "https://tarjetarojaenvivo.live/eventos/247-south-park",
      "meta": {
        "title": "24/7 South Park EN VIVO - Tarjeta Roja TV",
        "description": "Ver 24/7 South Park en vivo gratis el jueves 1 de enero de 1970",
        "keywords": "rojadirecta, tarjeta roja, rojadirecta tv, pirlotv, tarjeta roja tv, rojadirecta en vivo, tarjeta roja directa, tarjeta roja en vivo, pirlo tv rojadirecta, roja directa pirlo, tarjeta roja futbol en vivo, roja directa en vivo fútbol gratis, tarjeta roja fútbol en vivo, pirlo tv tarjeta roja, tarjeta roja tv en vivo, roja tv, la roja directa, rojadirecta tv en vivo, roja dirécta, 24/7 South Park, 24/7 Streams"
      },
      "event": {
        "start_time": "1970-01-01T00:00:00.000Z",
        "end_time": "1970-01-01T00:00:00.000Z",
        "status": "en vivo"
      },
      "technical": {
        "last_modified": "2025-12-20T02:01:01.197Z",
        "changefreq": "hourly",
        "priority": 0.85
      }
    },
    {
      "id": 3663,
      "slug": "24-7-cows",
      "canonical_url": "https://tarjetarojaenvivo.live/eventos/247-cows",
      "meta": {
        "title": "24/7 COWS EN VIVO - Tarjeta Roja TV",
        "description": "Ver 24/7 COWS en vivo gratis el sábado 18 de enero de 2025",
        "keywords": "rojadirecta, tarjeta roja, rojadirecta tv, pirlotv, tarjeta roja tv, rojadirecta en vivo, tarjeta roja directa, tarjeta roja en vivo, pirlo tv rojadirecta, roja directa pirlo, tarjeta roja futbol en vivo, roja directa en vivo fútbol gratis, tarjeta roja fútbol en vivo, pirlo tv tarjeta roja, tarjeta roja tv en vivo, roja tv, la roja directa, rojadirecta tv en vivo, roja dirécta, 24/7 COWS, 24/7 Streams"
      },
      "event": {
        "start_time": "2025-01-18T05:00:00.000Z",
        "end_time": "2025-02-28T20:00:00.000Z",
        "status": "en vivo"
      },
      "technical": {
        "last_modified": "2025-12-20T02:01:01.197Z",
        "changefreq": "hourly",
        "priority": 0.85
      }
    },
    {
      "id": 8008,
      "slug": "24-7-family-guy",
      "canonical_url": "https://tarjetarojaenvivo.live/eventos/247-family-guy",
      "meta": {
        "title": "24/7 Family Guy EN VIVO - Tarjeta Roja TV",
        "description": "Ver 24/7 Family Guy en vivo gratis el sábado 18 de enero de 2025",
        "keywords": "rojadirecta, tarjeta roja, rojadirecta tv, pirlotv, tarjeta roja tv, rojadirecta en vivo, tarjeta roja directa, tarjeta roja en vivo, pirlo tv rojadirecta, roja directa pirlo, tarjeta roja futbol en vivo, roja directa en vivo fútbol gratis, tarjeta roja fútbol en vivo, pirlo tv tarjeta roja, tarjeta roja tv en vivo, roja tv, la roja directa, rojadirecta tv en vivo, roja dirécta, 24/7 Family Guy, 24/7 Streams"
      },
      "event": {
        "start_time": "2025-01-18T08:00:00.000Z",
        "end_time": "2025-01-18T09:00:00.000Z",
        "status": "en vivo"
      },
      "technical": {
        "last_modified": "2025-12-20T02:01:01.197Z",
        "changefreq": "hourly",
        "priority": 0.85
      }
    },
    {
      "id": 5191,
      "slug": "24-7-the-simpsons",
      "canonical_url": "https://tarjetarojaenvivo.live/eventos/247-the-simpsons",
      "meta": {
        "title": "24/7 The Simpsons EN VIVO - Tarjeta Roja TV",
        "description": "Ver 24/7 The Simpsons en vivo gratis el sábado 18 de enero de 2025",
        "keywords": "rojadirecta, tarjeta roja, rojadirecta tv, pirlotv, tarjeta roja tv, rojadirecta en vivo, tarjeta roja directa, tarjeta roja en vivo, pirlo tv rojadirecta, roja directa pirlo, tarjeta roja futbol en vivo, roja directa en vivo fútbol gratis, tarjeta roja fútbol en vivo, pirlo tv tarjeta roja, tarjeta roja tv en vivo, roja tv, la roja directa, rojadirecta tv en vivo, roja dirécta, 24/7 The Simpsons, 24/7 Streams"
      },
      "event": {
        "start_time": "2025-01-18T10:28:00.000Z",
        "end_time": "2025-01-18T10:28:00.000Z",
        "status": "en vivo"
      },
      "technical": {
        "last_modified": "2025-12-20T02:01:01.197Z",
        "changefreq": "hourly",
        "priority": 0.85
      }
    },
    {
      "id": 10681,
      "slug": "master-stream-test",
      "canonical_url": "https://tarjetarojaenvivo.live/eventos/master-stream-test-delete-12568",
      "meta": {
        "title": "Master stream test EN VIVO - Tarjeta Roja TV",
        "description": "Ver Master stream test en vivo gratis el lunes 25 de agosto de 2025",
        "keywords": "rojadirecta, tarjeta roja, rojadirecta tv, pirlotv, tarjeta roja tv, rojadirecta en vivo, tarjeta roja directa, tarjeta roja en vivo, pirlo tv rojadirecta, roja directa pirlo, tarjeta roja futbol en vivo, roja directa en vivo fútbol gratis, tarjeta roja fútbol en vivo, pirlo tv tarjeta roja, tarjeta roja tv en vivo, roja tv, la roja directa, rojadirecta tv en vivo, roja dirécta, Master stream test, 24/7 Streams"
      },
      "event": {
        "start_time": "2025-08-25T06:00:00.000Z",
        "end_time": "2025-08-25T10:00:00.000Z",
        "status": "en vivo"
      },
      "technical": {
        "last_modified": "2025-12-20T02:01:01.197Z",
        "changefreq": "hourly",
        "priority": 0.85
      }
    }
  ]
}